yoo/__init__.py
yoo/yoo
yoo-0.1.1.data/scripts/yoo
yoo-0.1.1.dist-info/DESCRIPTION.rst
yoo-0.1.1.dist-info/METADATA
yoo-0.1.1.dist-info/RECORD
yoo-0.1.1.dist-info/WHEEL
yoo-0.1.1.dist-info/metadata.json
yoo-0.1.1.dist-info/top_level.txt
