Metadata-Version: 2.0
Name: yoo
Version: 0.1.1
Summary: react develop helper
Home-page: https://github.com/importcjj/init-react-webpack-project
Author: jiaju.chen
Author-email: jiaju.chen@ele.me
License: UNKNOWN
Platform: UNKNOWN
